pil_resize_aspect_ratio/__init__.py
pil_resize_aspect_ratio/resizer.py
pil_resize_aspect_ratio/enums/__init__.py
pil_resize_aspect_ratio/enums/fill_type.py
pil_resize_aspect_ratio-0.0.8.dist-info/LICENSE
pil_resize_aspect_ratio-0.0.8.dist-info/METADATA
pil_resize_aspect_ratio-0.0.8.dist-info/WHEEL
pil_resize_aspect_ratio-0.0.8.dist-info/top_level.txt
pil_resize_aspect_ratio-0.0.8.dist-info/RECORD
