Metadata-Version: 2.1
Name: pil-resize-aspect-ratio
Version: 0.0.8
Summary: pil_resize
Home-page: https://github.com/kkristof200/py_resize_image
Author: Kristóf-Attila Kovács
License: UNKNOWN
Platform: UNKNOWN
Classifier: Programming Language :: Python :: 3.4
Classifier: Programming Language :: Python :: 3.5
Classifier: Programming Language :: Python :: 3.6
Classifier: Programming Language :: Python :: 3.7
Classifier: Programming Language :: Python :: 3.8
Classifier: Programming Language :: Python :: 3.9
Classifier: License :: OSI Approved :: MIT License
Classifier: Operating System :: OS Independent
Requires-Python: >=3.4
Requires-Dist: noraise (>=0.0.10)
Requires-Dist: Pillow (>=8.1.0)
